{
  "show": "GU",
  "window": "rolling_last_7d",
  "window_start": "2026-07-09",
  "window_end": "2026-07-16",
  "window_start_mon": "2026-07-09",
  "window_end_sun": "2026-07-16",
  "generated_at": "2026-07-16T23:15:13.021322Z",
  "n": 2,
  "entries": [
    {
      "guest": "CMSGT. Dennis Fritz",
      "surname": "Fritz",
      "title": "CMSGT. Dennis Fritz: Israel's Influence Over Trump's Pentagon Is EVEN WORSE Than Under Bush!",
      "rumble_views": "0",
      "x_views": "183.5K",
      "date": "13 Jul",
      "yt_views": "901",
      "ig_likes": "0",
      "canonical_guest_full_name": "CMSGT. Dennis Fritz",
      "canonical_surname_upper": "FRITZ",
      "canonical_episode_id": "a34aff8a6180",
      "show": "GU"
    },
    {
      "guest": "James Carden",
      "surname": "Carden",
      "title": "Ukraine Proxy War: Europe's Elites & US Neocons Want the DISSOLUTION of Russia \u2014James Carden",
      "rumble_views": "0",
      "x_views": "403.6K",
      "date": "11 Jul",
      "yt_views": "1.1K",
      "ig_likes": "0",
      "canonical_guest_full_name": "James Carden",
      "canonical_surname_upper": "CARDEN",
      "canonical_episode_id": "a0bd191575b1",
      "show": "GU"
    }
  ],
  "source_feed": "videos.json",
  "rejected_count": 0,
  "rejected_sample": [],
  "_marker": "GU_WEEKLY_STATS_ROLLING7D_V2_2026_07_04"
}